<?xml version="1.0" encoding="UTF-8"?>

<!--
Company: Alteeve's Niche, Inc.
License: GPL v2+
Author:  Madison Kelly <mkelly@alteeve.ca>

This is the AN::Tools master 'words' file.
-->

<words>
	<meta version="3.0.0" languages="en_CA,jp"/>
	<!-- Canadian English -->
	<language name="en_CA" long_name="Canadian English" description="Striker/ScanCore language file.">
		
		<key name="brand_0001">Alteeve</key>
		<key name="brand_0002">Anvil!</key>
		<key name="brand_0003">Striker</key>
		<key name="brand_0004">ScanCore</key>
		<key name="brand_0005"><![CDATA[&copy; 2017 <a href="https://alteeve.com/" target="_new">Alteeve's Niche! Inc.</a>, Toronto, Ontario, Canada]]></key>
		<key name="brand_0006"><![CDATA[<i>Anvil!</i>]]></key>
		
		<key name="header_0001">Current Network Interfaces and States</key>
		<key name="header_0002">MAC Address</key>
		<key name="header_0003">Current Name</key>
		<key name="header_0004">Link State</key>
		<key name="header_0005">Link Speed (Mbps)</key>
		
		<!-- General strings shown in Striker -->
		<key name="striker_0001">Welcome! Lets setup your #!string!brand_0003!# dashboard...</key>
		<key name="striker_0002">We're going to ask you a few questions so that we can set things up for your environment. If you need help at any time, just click on the "[?]" icon in the top-right. Let's get started!</key>
		<key name="striker_0003">Organization name</key>
		<key name="striker_0004">This is the name of the company, organization or division that owns or maintains this #!string!brand_0006!#. This is a descriptive field and you can enter whatever makes most sense to you.</key>
		<key name="striker_0005">Prefix</key>
		<key name="striker_0006">This is a two to five character prefix used to identify this organization. It is used as the prefix for host names for dashboards, nodes and foundation pack equipment. You can use letters and numbers and set whatever makes sense to you.</key>
		<key name="striker_0007">Domain Name</key>
		<key name="striker_0008">This is the domain name you would like to use for this dashboard. This will also be used as the default domain used when creating new install manifests.</key>
		<key name="striker_0009">Sequence Number</key>
		<key name="striker_0010">If this is your first Striker, set this to '1'. If it is the second one, set '2'. If it is the third, '3' and so on.</key>
		<key name="striker_0011">Internet-Facing Network Count</key>
		<key name="striker_0012"><![CDATA[How many internal networks will this dashboard have access to? In most cases, this is just '1'.<br /><b>NOTE</b>: You must have a network interface for the back-channel network, plus one for each internal network. If you have two interfaces for each network, we will setup bonds for redundancy automatically.]]></key>
		<key name="striker_0013">Next</key>
		<key name="striker_0014">Step 1</key>
		<key name="striker_0015">IFN Count</key>
		<key name="striker_0016">Host name</key>
		<key name="striker_0017">This is the hostname for this Striker dashboard. Generally it is a good idea to stick with the default.</key>
		<key name="striker_0018">Back-Channel Network link #!variable!number!#:</key>
		<key name="striker_0019">This is where you configure the network to enable access this Back-Channel Network.</key>
		<key name="striker_0020">Storage Network link #!variable!number!#:</key>
		<key name="striker_0021">This is where you configure the network to enable access this Storage Network.</key>
		<key name="striker_0022">Internet-Facing Network link #!variable!number!#:</key>
		<key name="striker_0023">This is where you configure the network to enable access this Internet-Facing Network.</key>
		<key name="striker_0024">IP Address</key>
		<key name="striker_0025">Subnet</key>
		<key name="striker_0026">Gateway</key>
		<key name="striker_0027">DNS Server</key>
		<key name="striker_0028">Network Interface</key>
		<key name="striker_0029">Primary Interface</key>
		<key name="striker_0030">Backup Interface</key>
		<key name="striker_0031">Striker user name</key>
		<key name="striker_0032">This is the user name that you will log into Striker as and the name of the user that owns the database.</key>
		<key name="striker_0033">Striker password</key>
		<key name="striker_0034"><![CDATA[This will be the password used to log into this Striker and connect to its database.<br /><b>NOTE</b>: This password needs to be stored in plain text. Do not use a password you use elsewhere.]]></key>
		
		<!-- Errors -->
		<key name="striker_error_0001">There are not enough network interfaces on this machine. You have: [#!variable!interface_count!#] interface(s), and you need at least: [#!variable!required_interfaces_for_single!#] interfaces to connect to the requested networks (one for Back-Channel and one for each Internet-Facing network).</key>
		
		<!-- These are works and strings used by javascript/jqery -->
		<key name="js_0001">Up</key>
		<key name="js_0002">Down</key>
		<key name="js_0003">Mbps</key>
		
	</language>
	<!-- 日本語 -->
	<language name="jp" long_name="日本語" description="Striker/ScanCore language file.">
		
		<key name="brand_0001">アルティーブ</key>
		<key name="brand_0002">Anvil!</key>
		<key name="brand_0003">ストライカ</key>
		<key name="brand_0004">スカンコア</key>
		<key name="brand_0005"><![CDATA[&copy; 2017 <a href="https://alteeve.com/" target="_new">Alteeve's Niche! Inc.</a>, トロント、オンタリオ、カナダ]]></key>
		
	</language>
</words>
